{
  "item": {
    "name": "Yasha Sune-ate of Striking",
    "jobCategories": "PGL MNK SAM",
    "id": 11637,
    "patch": 3.0,
    "patchCategory": 0,
    "price": 49985,
    "ilvl": 170,
    "category": 38,
    "unique": 1,
    "dyecount": 0,
    "sell_price": 500,
    "rarity": 3,
    "convertable": 1,
    "unlistable": 1,
    "stackSize": 1,
    "repair": 12,
    "equip": 1,
    "repair_item": 10386,
    "glamourous": 1,
    "delivery": 978,
    "slot": 8,
    "elvl": 60,
    "jobs": 65,
    "models": [
      "244-1-0-0"
    ],
    "attr": {
      "Defense": 124,
      "Magic Defense": 124,
      "Strength": 40,
      "Vitality": 39,
      "Skill Speed": 47,
      "Direct Hit Rate": 33
    },
    "icon": 46451,
    "sharedModels": [
      11636,
      11639,
      11712,
      11713,
      11715,
      18605,
      18611,
      18623
    ],
    "tradeCurrency": [
      {
        "shop": "Doman Gear Reoutfitting (DoW) I",
        "npcs": [
          1013747
        ],
        "listings": [
          {
            "item": [
              {
                "id": "11713",
                "amount": 1
              }
            ],
            "currency": [
              {
                "id": "11637",
                "amount": 1
              },
              {
                "id": "28",
                "amount": 100
              }
            ]
          }
        ]
      }
    ]
  },
  "partials": [
    {
      "type": "item",
      "id": "11636",
      "obj": {
        "i": 11636,
        "n": "Yasha Sune-ate of Maiming",
        "l": 170,
        "c": 46452,
        "t": 38
      }
    },
    {
      "type": "item",
      "id": "11639",
      "obj": {
        "i": 11639,
        "n": "Yasha Sune-ate of Scouting",
        "l": 170,
        "c": 46453,
        "t": 38
      }
    },
    {
      "type": "item",
      "id": "11712",
      "obj": {
        "i": 11712,
        "n": "Asuran Sune-ate of Maiming",
        "l": 180,
        "c": 46452,
        "t": 38
      }
    },
    {
      "type": "item",
      "id": "11713",
      "obj": {
        "i": 11713,
        "n": "Asuran Sune-ate of Striking",
        "l": 180,
        "c": 46451,
        "t": 38
      }
    },
    {
      "type": "item",
      "id": "11715",
      "obj": {
        "i": 11715,
        "n": "Asuran Sune-ate of Scouting",
        "l": 180,
        "c": 46453,
        "t": 38
      }
    },
    {
      "type": "item",
      "id": "18605",
      "obj": {
        "i": 18605,
        "n": "Yanxian Sune-ate of Maiming",
        "l": 282,
        "c": 46752,
        "t": 38
      }
    },
    {
      "type": "item",
      "id": "18611",
      "obj": {
        "i": 18611,
        "n": "Yanxian Sune-ate of Striking",
        "l": 282,
        "c": 46753,
        "t": 38
      }
    },
    {
      "type": "item",
      "id": "18623",
      "obj": {
        "i": 18623,
        "n": "Yanxian Sune-ate of Scouting",
        "l": 282,
        "c": 46754,
        "t": 38
      }
    },
    {
      "type": "npc",
      "id": "1013747",
      "obj": {
        "i": 1013747,
        "n": "Seika",
        "l": 2082,
        "s": 22,
        "t": "Gear Improvement",
        "r": 1,
        "a": 2094,
        "c": [
          6.74,
          7.45
        ]
      }
    },
    {
      "type": "item",
      "id": "28",
      "obj": {
        "i": 28,
        "n": "Allagan Tomestone of Poetics",
        "l": 1,
        "c": 65023,
        "t": 63
      }
    }
  ]
}