{
  "item": {
    "name": "Lunaris Rod Awoken Replica",
    "jobCategories": "BLM",
    "id": 13785,
    "patch": 3.25,
    "patchCategory": 0,
    "price": 100,
    "ilvl": 1,
    "category": 7,
    "unique": 1,
    "dyecount": 0,
    "rarity": 3,
    "convertable": 1,
    "unlistable": 1,
    "stackSize": 1,
    "repair": 11,
    "equip": 1,
    "repair_item": 10386,
    "glamourous": 1,
    "slot": 13,
    "elvl": 60,
    "jobs": 26,
    "models": [
      "1001-13-2-0"
    ],
    "attr": {
      "Physical Damage": 9,
      "Magic Damage": 9,
      "Delay": 3.28
    },
    "icon": 33036,
    "sharedModels": [
      10293,
      11774,
      13606,
      13620
    ],
    "vendors": [
      1016596
    ]
  },
  "partials": [
    {
      "type": "item",
      "id": "10293",
      "obj": {
        "i": 10293,
        "n": "Antiquated Lunaris Rod",
        "l": 200,
        "c": 33036,
        "t": 7
      }
    },
    {
      "type": "item",
      "id": "11774",
      "obj": {
        "i": 11774,
        "n": "Lunaris Rod",
        "l": 210,
        "c": 33036,
        "t": 7
      }
    },
    {
      "type": "item",
      "id": "13606",
      "obj": {
        "i": 13606,
        "n": "Lunaris Rod Awoken",
        "l": 200,
        "c": 33036,
        "t": 7
      }
    },
    {
      "type": "item",
      "id": "13620",
      "obj": {
        "i": 13620,
        "n": "Animated Lunaris Rod",
        "l": 170,
        "c": 33036,
        "t": 7
      }
    },
    {
      "type": "npc",
      "id": "1016596",
      "obj": {
        "i": 1016596,
        "n": "Restoration Node",
        "l": 2101,
        "s": 7,
        "a": 2131,
        "c": [
          7.15,
          11.27
        ]
      }
    }
  ]
}