{
  "item": {
    "name": "Faded Copy of Good King Moggle Mog XII",
    "description": "Timeworn pages of sheet music containing the full score for <span class=\"emphasis\">Good King Moggle Mog XII</span>.",
    "id": 15836,
    "patch": 3.3,
    "patchCategory": 16,
    "price": 7,
    "ilvl": 1,
    "category": 94,
    "dyecount": 0,
    "tradeable": 1,
    "sell_price": 1,
    "rarity": 1,
    "stackSize": 999,
    "icon": 25958,
    "instances": [
      20012,
      20012
    ],
    "ingredient_of": {
      "15821": 1
    },
    "alla": {
      "source": [
        "INSTANCE"
      ]
    }
  },
  "partials": [
    {
      "type": "instance",
      "id": "20012",
      "obj": {
        "i": 20012,
        "n": "Thornmarch (Extreme)",
        "c": 61804,
        "t": "Trials",
        "min_lvl": 50,
        "max_lvl": 50,
        "min_ilvl": 80
      }
    },
    {
      "type": "item",
      "id": "15821",
      "obj": {
        "i": 15821,
        "n": "Good King Moggle Mog XII Orchestrion Roll",
        "l": 1,
        "c": 25945,
        "t": 94
      }
    }
  ]
}