{
  "item": {
    "name": "Gazelle Horn",
    "description": "The twisted horn of a gazelle.",
    "id": 19920,
    "patch": 4.0,
    "patchCategory": 5,
    "price": 548,
    "ilvl": 282,
    "category": 53,
    "dyecount": 0,
    "tradeable": 1,
    "sell_price": 4,
    "rarity": 1,
    "stackSize": 999,
    "icon": 22206,
    "drops": [
      66640000006280,
      66640000005697
    ],
    "instances": [
      50,
      52,
      53,
      54,
      55,
      58,
      59,
      60,
      61,
      63,
      62,
      64
    ],
    "ingredient_of": {
      "19553": 1,
      "19558": 1,
      "19884": 1,
      "18985": 2,
      "18991": 1,
      "18997": 1,
      "19009": 1
    },
    "leves": [
      1322,
      1324
    ],
    "ventures": [
      721
    ]
  },
  "partials": [
    {
      "type": "instance",
      "id": "50",
      "obj": {
        "i": 50,
        "n": "Shisui of the Violet Tides",
        "c": 61801,
        "t": "Dungeons",
        "min_lvl": 63,
        "max_lvl": 64,
        "min_ilvl": 245
      }
    },
    {
      "type": "instance",
      "id": "52",
      "obj": {
        "i": 52,
        "n": "The Sirensong Sea",
        "c": 61801,
        "t": "Dungeons",
        "min_lvl": 61,
        "max_lvl": 62,
        "min_ilvl": 240
      }
    },
    {
      "type": "instance",
      "id": "53",
      "obj": {
        "i": 53,
        "n": "Bardam's Mettle",
        "c": 61801,
        "t": "Dungeons",
        "min_lvl": 65,
        "max_lvl": 66,
        "min_ilvl": 250
      }
    },
    {
      "type": "instance",
      "id": "54",
      "obj": {
        "i": 54,
        "n": "Doma Castle",
        "c": 61801,
        "t": "Dungeons",
        "min_lvl": 67,
        "max_lvl": 68,
        "min_ilvl": 255
      }
    },
    {
      "type": "instance",
      "id": "55",
      "obj": {
        "i": 55,
        "n": "Castrum Abania",
        "c": 61801,
        "t": "Dungeons",
        "min_lvl": 69,
        "max_lvl": 70,
        "min_ilvl": 260,
        "max_ilvl": 290
      }
    },
    {
      "type": "instance",
      "id": "58",
      "obj": {
        "i": 58,
        "n": "The Drowned City of Skalla",
        "c": 61801,
        "t": "Dungeons",
        "min_lvl": 70,
        "max_lvl": 70,
        "min_ilvl": 300,
        "max_ilvl": 370
      }
    },
    {
      "type": "instance",
      "id": "59",
      "obj": {
        "i": 59,
        "n": "Hells' Lid",
        "c": 61801,
        "t": "Dungeons",
        "min_lvl": 70,
        "max_lvl": 70,
        "min_ilvl": 310
      }
    },
    {
      "type": "instance",
      "id": "60",
      "obj": {
        "i": 60,
        "n": "The Fractal Continuum (Hard)",
        "c": 61801,
        "t": "Dungeons",
        "min_lvl": 70,
        "max_lvl": 70,
        "min_ilvl": 310
      }
    },
    {
      "type": "instance",
      "id": "61",
      "obj": {
        "i": 61,
        "n": "The Swallow's Compass",
        "c": 61801,
        "t": "Dungeons",
        "min_lvl": 70,
        "max_lvl": 70,
        "min_ilvl": 330
      }
    },
    {
      "type": "instance",
      "id": "63",
      "obj": {
        "i": 63,
        "n": "The Burn",
        "c": 61801,
        "t": "Dungeons",
        "min_lvl": 70,
        "max_lvl": 70,
        "min_ilvl": 340
      }
    },
    {
      "type": "instance",
      "id": "62",
      "obj": {
        "i": 62,
        "n": "Saint Mocianne's Arboretum (Hard)",
        "c": 61801,
        "t": "Dungeons",
        "min_lvl": 70,
        "max_lvl": 70,
        "min_ilvl": 340
      }
    },
    {
      "type": "instance",
      "id": "64",
      "obj": {
        "i": 64,
        "n": "The Ghimlyt Dark",
        "c": 61801,
        "t": "Dungeons",
        "min_lvl": 70,
        "max_lvl": 70,
        "min_ilvl": 360
      }
    },
    {
      "type": "item",
      "id": "19553",
      "obj": {
        "i": 19553,
        "n": "Gazelle Horn Needle",
        "l": 245,
        "c": 35522,
        "t": 22,
        "p": 34927
      }
    },
    {
      "type": "item",
      "id": "19558",
      "obj": {
        "i": 19558,
        "n": "Gazelle Horn Fishing Rod",
        "l": 245,
        "c": 38225,
        "t": 32,
        "p": 34927
      }
    },
    {
      "type": "item",
      "id": "19884",
      "obj": {
        "i": 19884,
        "n": "Cunning Craftsman's Tea",
        "l": 282,
        "c": 24411,
        "t": 44
      }
    },
    {
      "type": "item",
      "id": "18985",
      "obj": {
        "i": 18985,
        "n": "Chromite Helm of Fending",
        "l": 320,
        "c": 40275,
        "t": 34
      }
    },
    {
      "type": "item",
      "id": "18991",
      "obj": {
        "i": 18991,
        "n": "Palladium Circlet of Maiming",
        "l": 320,
        "c": 41700,
        "t": 34
      }
    },
    {
      "type": "item",
      "id": "18997",
      "obj": {
        "i": 18997,
        "n": "Palladium Circlet of Striking",
        "l": 320,
        "c": 41701,
        "t": 34
      }
    },
    {
      "type": "item",
      "id": "19009",
      "obj": {
        "i": 19009,
        "n": "Palladium Circlet of Scouting",
        "l": 320,
        "c": 41702,
        "t": 34
      }
    },
    {
      "type": "mob",
      "id": "66640000005697",
      "obj": {
        "i": 66640000005697,
        "n": "Gazelle",
        "l": "67",
        "z": 2406
      }
    },
    {
      "type": "mob",
      "id": "66640000006280",
      "obj": {
        "i": 66640000006280,
        "n": "Stray Gazelle",
        "l": "68",
        "z": 2407
      }
    },
    {
      "type": "leve",
      "id": "1322",
      "obj": {
        "i": 1322,
        "n": "Edge of the Arcane",
        "l": 66,
        "j": 15,
        "p": 2404
      }
    },
    {
      "type": "leve",
      "id": "1324",
      "obj": {
        "i": 1324,
        "n": "Let Loose the Juice",
        "l": 66,
        "j": 15,
        "p": 2404
      }
    }
  ]
}