{
  "item": {
    "name": "The Green Jester",
    "description": "A king among clown loaches.<br><br>[Suitable for printing on large canvases.]",
    "fish": {
      "guide": "A night in the foul belly of a morbol was not nearly enough to finish off this hardy loach, and if anything he emerged from the seedkin's nethers the following morn even stronger, if not a touch more green.",
      "icon": 79354,
      "weatherRestricted": 1,
      "spots": [
        {
          "spot": 5,
          "hookset": "Powerful Hookset",
          "tug": "Heavy",
          "ff14anglerId": 270,
          "baits": [
            [
              2599
            ]
          ]
        }
      ]
    },
    "id": 7934,
    "patch": 2.3,
    "patchCategory": 7,
    "price": 950,
    "ilvl": 80,
    "category": 47,
    "dyecount": 0,
    "tradeable": 1,
    "sell_price": 29,
    "rarity": 2,
    "stackSize": 999,
    "repair": 15,
    "icon": 29354,
    "fishingSpots": [
      5
    ],
    "desynthedTo": [
      7045,
      5826,
      5267
    ]
  },
  "partials": [
    {
      "type": "fishing",
      "id": "5",
      "obj": {
        "i": 5,
        "n": "Hopeseed Pond",
        "l": 35,
        "c": 1,
        "z": 54,
        "x": 14.81,
        "y": 21.24
      }
    },
    {
      "type": "item",
      "id": "2599",
      "obj": {
        "i": 2599,
        "n": "Honey Worm",
        "l": 35,
        "c": 27018,
        "t": 33,
        "p": 8
      }
    },
    {
      "type": "item",
      "id": "7045",
      "obj": {
        "i": 7045,
        "n": "Morbol Saliva",
        "l": 45,
        "c": 22603,
        "t": 54
      }
    },
    {
      "type": "item",
      "id": "5826",
      "obj": {
        "i": 5826,
        "n": "Allagan Gold Piece",
        "l": 35,
        "c": 26001,
        "t": 61
      }
    },
    {
      "type": "item",
      "id": "5267",
      "obj": {
        "i": 5267,
        "n": "Fine Sand",
        "l": 2,
        "c": 21464,
        "t": 48
      }
    }
  ]
}